odoo/addons/website_sale_search_no_kept/README.rst
odoo/addons/website_sale_search_no_kept/__init__.py
odoo/addons/website_sale_search_no_kept/__manifest__.py
odoo/addons/website_sale_search_no_kept/controllers/__init__.py
odoo/addons/website_sale_search_no_kept/controllers/main.py
odoo/addons/website_sale_search_no_kept/i18n/website_sale_search_no_kept.pot
odoo/addons/website_sale_search_no_kept/readme/CONTRIBUTORS.rst
odoo/addons/website_sale_search_no_kept/readme/DESCRIPTION.rst
odoo/addons/website_sale_search_no_kept/readme/USAGE.rst
odoo/addons/website_sale_search_no_kept/static/description/icon.png
odoo/addons/website_sale_search_no_kept/static/description/index.html
odoo/addons/website_sale_search_no_kept/static/src/js/website_sale_search_no_kept_tour.js
odoo/addons/website_sale_search_no_kept/tests/__init__.py
odoo/addons/website_sale_search_no_kept/tests/test_website_sale_search_no_kept.py
odoo/addons/website_sale_search_no_kept/views/assets.xml
odoo11_addon_website_sale_search_no_kept-11.0.1.0.0.99.dev3.dist-info/METADATA
odoo11_addon_website_sale_search_no_kept-11.0.1.0.0.99.dev3.dist-info/WHEEL
odoo11_addon_website_sale_search_no_kept-11.0.1.0.0.99.dev3.dist-info/top_level.txt
odoo11_addon_website_sale_search_no_kept-11.0.1.0.0.99.dev3.dist-info/RECORD
